{
  "paper_id": 436,
  "title": "Buckaroo: A Direct Manipulation Visual Data Wrangler",
  "authors": "Annabelle Warner, Andrew Mcnutt, Paul Rosen, El Kindi Rezig",
  "summary": {"objective": "데이터 전처리를 위한 직접 조작 시각적 도구", "methodology": "직접 조작 인터페이스로 데이터 랭글링 자동화", "contributions": ["시각적 데이터 랭글러 Buckaroo", "직접 조작 인터페이스"], "experiments": "데이터 전처리 작업에서 효율성 검증", "limitations": "복잡한 변환 표현"},
  "tags": [{"tag": "Data Cleaning", "confidence": 0.95}, {"tag": "Data Integration", "confidence": 0.9}, {"tag": "Data Quality", "confidence": 0.85}],
  "key_findings": ["직접 조작이 데이터 랭글링에 효과적", "사용자 친화적 인터페이스"]
}
