{
  "paper_id": 69,
  "title": "IcedTea: Efficient and Responsive Time-Travel Debugging in Dataflow Systems",
  "authors": "Shengquan Ni, Yicong Huang, Zuozhi Wang, Chen Li",
  "summary": {
    "objective": "데이터플로우 시스템에서 역방향 디버깅을 지원하는 시간 여행 디버깅 패러다임 제시",
    "methodology": "사용자가 주기적으로 작업과 상호작용하여 연산자의 전역 상태 검색. 실행 후 과거 상호작용으로 데이터플로우 상태 롤백. 스텝 명령으로 과거 실행 재현",
    "contributions": [
      "시간 여행 디버깅 패러다임 IcedTea",
      "런타임 오버헤드 감소 기법",
      "반응적 디버깅 명령 지원"
    ],
    "experiments": "런타임 오버헤드 감소와 반응적 디버깅 지원",
    "limitations": "매우 긴 실행에서의 상태 저장 비용"
  },
  "tags": [
    {
      "tag": "Distributed Systems",
      "confidence": 0.9
    },
    {
      "tag": "Data Quality",
      "confidence": 0.85
    },
    {
      "tag": "Performance",
      "confidence": 0.8
    }
  ],
  "key_findings": [
    "역방향 디버깅이 데이터플로우에서 가치 있음",
    "주기적 상태 저장이 롤백에 핵심"
  ]
}